{
  "whatsapp-brands-solid-full": 61697,
  "viber-brands-solid-full": 61698,
  "users-solid-full": 61699,
  "stethoscope-solid-full": 61700,
  "square-check-solid-full": 61701,
  "phone-solid-full": 61702,
  "map-location-dot-solid-full": 61703,
  "language-solid-full": 61704,
  "facebook-f-brands-solid-full": 61705,
  "envelope-solid-full": 61706,
  "clock-solid-full": 61707,
  "circle-plus-solid-full": 61708,
  "circle-minus-solid-full": 61709,
  "child-solid-full": 61710,
  "chevron-up-solid-full": 61711,
  "chevron-right-solid-full": 61712,
  "chevron-left-solid-full": 61713,
  "chevron-down-solid-full": 61714,
  "calendar-solid-full": 61715,
  "briefcase-solid-full": 61716,
  "bolt-solid-full": 61717
}